plotnineseqsuite/__init__.py
plotnineseqsuite/align.py
plotnineseqsuite/bar.py
plotnineseqsuite/col_schemes.py
plotnineseqsuite/common.py
plotnineseqsuite/logo.py
plotnineseqsuite/theme.py
plotnineseqsuite/tool.py
plotnineseqsuite/data/__init__.py
plotnineseqsuite/font/__init__.py
plotnineseqsuite/font/akrobat_bold.csv
plotnineseqsuite/font/akrobat_regular.csv
plotnineseqsuite/font/arial.csv
plotnineseqsuite/font/courier_new.csv
plotnineseqsuite/font/helvetica_bold.csv
plotnineseqsuite/font/helvetica_light.csv
plotnineseqsuite/font/helvetica_regular.csv
plotnineseqsuite/font/roboto_bold.csv
plotnineseqsuite/font/roboto_medium.csv
plotnineseqsuite/font/roboto_regular.csv
plotnineseqsuite/font/roboto_slab_bold.csv
plotnineseqsuite/font/roboto_slab_light.csv
plotnineseqsuite/font/roboto_slab_regular.csv
plotnineseqsuite/font/times_new_roman.csv
plotnineseqsuite/font/xkcd_regular.csv
plotnineseqsuite-1.2.1.dist-info/licenses/LICENSE
plotnineseqsuite-1.2.1.dist-info/METADATA
plotnineseqsuite-1.2.1.dist-info/WHEEL
plotnineseqsuite-1.2.1.dist-info/top_level.txt
plotnineseqsuite-1.2.1.dist-info/RECORD
